inboxzero/__init__.py
inboxzero/__main__.py
inboxzero/background.py
inboxzero/cli.py
inboxzero/core.py
inboxzero/db.py
inboxzero/notifyer.py
inboxzero/screen.py
inboxzero-0.0.3.dist-info/METADATA
inboxzero-0.0.3.dist-info/WHEEL
inboxzero-0.0.3.dist-info/entry_points.txt
inboxzero-0.0.3.dist-info/top_level.txt
inboxzero-0.0.3.dist-info/RECORD
