Metadata-Version: 2.4
Name: inboxzero
Version: 0.0.3
Summary: A minimal IMAP/SMTP terminal client designed for fast, keyboard-driven email triage.Features include new-email notifications, inbox listing, and a lightweight message composer.
Author-email: madushanka rajapakshe <MadushankaRajapaksha999@gmail.com>
License: MIT
Project-URL: Homepage, https://github.com/MadushankaRajapaksha/Inbox-Zero-
Project-URL: Bug Tracker, https://github.com/MadushankaRajapaksha/Inbox-Zero-/issues
Classifier: Programming Language :: Python :: 3
Classifier: License :: OSI Approved :: MIT License
Classifier: Operating System :: OS Independent
Requires-Python: >=3.8
Requires-Dist: rich>=10.0.0
Requires-Dist: typer>=0.9.0
Requires-Dist: textual>=0.1.0
Requires-Dist: python-dotenv>=1.0.0
